number_abbreviations/__init__.py
number_abbreviations/num_abbr.py
number_abbreviations-1.3.dist-info/METADATA
number_abbreviations-1.3.dist-info/WHEEL
number_abbreviations-1.3.dist-info/top_level.txt
number_abbreviations-1.3.dist-info/RECORD
