Metadata-Version: 2.1
Name: number-abbreviations
Version: 1.3
Summary: converts abreviated numbers to their full form
Home-page: UNKNOWN
Author: Josh Shrawder
Author-email: joshshrawder@gmail.com
License: MIT
Platform: UNKNOWN
